attpc_spyral-1.0.0.dist-info/METADATA
attpc_spyral-1.0.0.dist-info/WHEEL
attpc_spyral-1.0.0.dist-info/entry_points.txt
attpc_spyral-1.0.0.dist-info/licenses/LICENSE
spyral/__init__.py
spyral/core/__init__.py
spyral/core/cluster.py
spyral/core/clusterize.py
spyral/core/config.py
spyral/core/constants.py
spyral/core/dragon_start.py
spyral/core/estimator.py
spyral/core/hardware_id.py
spyral/core/legacy_beam_pads.py
spyral/core/pad_map.py
spyral/core/phase.py
spyral/core/pipeline.py
spyral/core/point_cloud.py
spyral/core/run_stacks.py
spyral/core/schema.py
spyral/core/spy_log.py
spyral/core/status_message.py
spyral/core/track_generator.py
spyral/correction/__init__.py
spyral/correction/electron_corrector.py
spyral/correction/generate.py
spyral/data/__init__.py
spyral/data/pad_gain_map.csv
spyral/data/pad_scale.csv
spyral/data/pad_time_correction.csv
spyral/data/padxy.csv
spyral/geometry/__init__.py
spyral/geometry/circle.py
spyral/interpolate/__init__.py
spyral/interpolate/bilinear.py
spyral/interpolate/linear.py
spyral/interpolate/track_interpolator.py
spyral/phases/__init__.py
spyral/phases/cluster_phase.py
spyral/phases/estimation_phase.py
spyral/phases/interp_solver_phase.py
spyral/phases/pointcloud_phase.py
spyral/phases/schema.py
spyral/solvers/__init__.py
spyral/solvers/guess.py
spyral/solvers/solver_interp.py
spyral/solvers/solver_interp_leastsq.py
spyral/trace/__init__.py
spyral/trace/frib_event.py
spyral/trace/frib_scalers.py
spyral/trace/frib_trace.py
spyral/trace/get_event.py
spyral/trace/get_trace.py
spyral/trace/peak.py
spyral/trace/trace_reader.py
attpc_spyral-1.0.0.dist-info/RECORD
