Metadata-Version: 2.1
Name: attpc_spyral
Version: 1.0.0
Summary: AT-TPC analysis pipeline
Author-Email: gwm17 <gordonmccann215@gmail.com>, turinath <turi@frib.msu.edu>
License:                     GNU GENERAL PUBLIC LICENSE
Classifier: Intended Audience :: Science/Research
Classifier: License :: OSI Approved :: GNU General Public License v3 (GPLv3)
Classifier: Operating System :: Microsoft :: Windows :: Windows 10
Classifier: Operating System :: Microsoft :: Windows :: Windows 11
Classifier: Operating System :: MacOS
Classifier: Operating System :: POSIX :: Linux
Classifier: Programming Language :: Python :: 3
Classifier: Programming Language :: Python :: 3.10
Classifier: Programming Language :: Python :: 3.11
Classifier: Programming Language :: Python :: 3.12
Classifier: Topic :: Scientific/Engineering :: Physics
Classifier: Typing :: Typed
Project-URL: Documentation, https://attpc.github.io/Spyral
Project-URL: Repository, https://github.com/ATTPC/Spyral
Project-URL: Issues, https://github.com/ATTPC/Spyral/issues
Requires-Python: <3.13,>=3.10
Requires-Dist: spyral-utils>=2.0.0
Requires-Dist: contourpy>=1.2.1
Requires-Dist: h5py>=3.11.0
Requires-Dist: lmfit>=1.3.0
Requires-Dist: numba>=0.61.0
Requires-Dist: scikit-learn>=1.4.2
Requires-Dist: tqdm>=4.65.0
Requires-Dist: rocket-fft>=0.2.5
Requires-Dist: typing-extensions>=4.11.0
Requires-Dist: psutil>=5.9.8
Requires-Dist: python-dotenv>=1.0.1
